{"course_name": "M\u00e1ster en Prevenci\u00f3n y C\u00e1ncer Hereditario", "category": "salud", "plan": {"1\u00ba": {"periodos": {"Primer cuatrimestre": {"asignaturas": [{"id": "1748877", "name": "Prevenci\u00f3n y Diagn\u00f3stico del C\u00e1ncer", "curso": "1\u00ba", "id_curso": "89", "ects": "6", "itinerario": false, "id_itinerario": null, "periodo": "Primer cuatrimestre", "id_periodo": "92", "tipo": "obligatoria", "id_tipo": "96", "detalle_url": "https://static.unir.net/guias_espana/guias_nuevas/mch01_prevencion.htm", "product_id": "42273", "notas": " ", "unir_id": "AS-PREV000YDIAG-2104121341", "description": "Prevenci\u00f3n y Diagn\u00f3stico del C\u00e1ncer"}, {"id": "1748880", "name": "Gen\u00e9tica del C\u00e1ncer y Estudio de la Predisposici\u00f3n Gen\u00e9tica al C\u00e1ncer", "curso": "1\u00ba", "id_curso": "89", "ects": "6", "itinerario": false, "id_itinerario": null, "periodo": "Primer cuatrimestre", "id_periodo": "92", "tipo": "obligatoria", "id_tipo": "96", "detalle_url": "https://static.unir.net/guias_espana/guias_nuevas/mch02_genetica.htm", "product_id": "43488", "notas": null, "unir_id": null, "description": "Gen\u00e9tica del C\u00e1ncer y Estudio de la Predisposici\u00f3n Gen\u00e9tica al C\u00e1ncer"}, {"id": "1748883", "name": "Asesoramiento del Riesgo de C\u00e1ncer y Proceso de Consejo Gen\u00e9tico en C\u00e1ncer", "curso": "1\u00ba", "id_curso": "89", "ects": "6", "itinerario": false, "id_itinerario": null, "periodo": "Primer cuatrimestre", "id_periodo": "92", "tipo": "obligatoria", "id_tipo": "96", "detalle_url": "https://static.unir.net/guias_espana/guias_nuevas/mch03_asesoramiento.htm", "product_id": "42276", "notas": " ", "unir_id": "AS-ASES0DELRIES-2104121342", "description": "Asesoramiento del Riesgo de C\u00e1ncer y Proceso de Consejo Gen\u00e9tico en C\u00e1ncer"}, {"id": "1748886", "name": "Aspectos \u00c9ticos, Legales y Sociales en los Estudios Gen\u00e9ticos y en la Prevenci\u00f3n del C\u00e1ncer", "curso": "1\u00ba", "id_curso": "89", "ects": "6", "itinerario": false, "id_itinerario": null, "periodo": "Primer cuatrimestre", "id_periodo": "92", "tipo": "obligatoria", "id_tipo": "96", "detalle_url": "https://static.unir.net/guias_espana/guias_nuevas/mch04_aspectos_eticos.htm", "product_id": "42279", "notas": " ", "unir_id": "AS-ASPE\u00c9TILEGA-2104121342", "description": "Aspectos \u00c9ticos, Legales y Sociales en los Estudios Gen\u00e9ticos y en la Prevenci\u00f3n del C\u00e1ncer"}, {"id": "1748892", "name": "S\u00edndromes Hereditarios de C\u00e1ncer", "curso": "1\u00ba", "id_curso": "89", "ects": "6", "itinerario": false, "id_itinerario": null, "periodo": "Primer cuatrimestre", "id_periodo": "92", "tipo": "obligatoria", "id_tipo": "96", "detalle_url": "https://static.unir.net/guias_espana/guias_nuevas/mch05_sindromes.htm", "product_id": "42282", "notas": " ", "unir_id": "AS-S\u00edNHERE00DE-2104121342", "description": "S\u00edndromes Hereditarios de C\u00e1ncer"}], "_optativas_fuera": true, "optativas_ects": "30"}, "Segundo cuatrimestre": {"asignaturas": [{"id": "1748895", "name": "Investigaci\u00f3n Traslacional: Aspectos Terap\u00e9uticos de los Estudios Moleculares en C\u00e1ncer", "curso": "1\u00ba", "id_curso": "89", "ects": "6", "itinerario": false, "id_itinerario": null, "periodo": "Segundo cuatrimestre", "id_periodo": "91", "tipo": "obligatoria", "id_tipo": "96", "detalle_url": "https://static.unir.net/guias_espana/guias_nuevas/mch06_investigacion_traslacional.htm", "product_id": "42285", "notas": " ", "unir_id": "AS-INVETRASASPE-2104121342", "description": "Investigaci\u00f3n Traslacional: Aspectos Terap\u00e9uticos de los Estudios Moleculares en C\u00e1ncer"}, {"id": "1748898", "name": "Metodolog\u00eda de la Investigaci\u00f3n", "curso": "1\u00ba", "id_curso": "89", "ects": "6", "itinerario": false, "id_itinerario": null, "periodo": "Segundo cuatrimestre", "id_periodo": "91", "tipo": "obligatoria", "id_tipo": "96", "detalle_url": "https://static.unir.net/guias_espana/guias_nuevas/mch07_metodologia.htm", "product_id": "42288", "notas": " ", "unir_id": "AS-METO00DE00LA-2104121343", "description": "Metodolog\u00eda de la Investigaci\u00f3n"}, {"id": "1748901", "name": "Sistemas de Gesti\u00f3n de la Calidad en el Diagn\u00f3stico e Investigaci\u00f3n Oncol\u00f3gica", "curso": "1\u00ba", "id_curso": "89", "ects": "6", "itinerario": false, "id_itinerario": null, "periodo": "Segundo cuatrimestre", "id_periodo": "91", "tipo": "obligatoria", "id_tipo": "96", "detalle_url": "https://static.unir.net/guias_espana/guias_nuevas/mch08_sistemas_calidad.htm", "product_id": "42291", "notas": " ", "unir_id": "AS-SIST00DEGEST-2104121343", "description": "Sistemas de Gesti\u00f3n de la Calidad en el Diagn\u00f3stico e Investigaci\u00f3n Oncol\u00f3gica"}, {"id": "1748904", "name": "Proyecto Final", "curso": "1\u00ba", "id_curso": "89", "ects": "12", "itinerario": false, "id_itinerario": null, "periodo": "Segundo cuatrimestre", "id_periodo": "91", "tipo": "Trabajo Fin de M\u00e1ster", "id_tipo": "729", "detalle_url": "https://static.unir.net/guias_espana/guias_nuevas/mch09_proyecto_final.htm", "product_id": "42294", "notas": " ", "unir_id": "AS-PROYFINA-2104121343", "description": "Proyecto Final"}], "_optativas_fuera": true, "optativas_ects": "30"}}}}}